psgv/__init__.py
psgv/psgv.py
psgv-0.1.dist-info/METADATA
psgv-0.1.dist-info/WHEEL
psgv-0.1.dist-info/top_level.txt
psgv-0.1.dist-info/RECORD
