Metadata-Version: 2.1
Name: psgv
Version: 0.1
Summary: Python System Global Variables
Home-page: https://github.com/alexhagen/psgv
Author: Alex Hagen
Author-email: alexhagen6@gmail.com
License: UNKNOWN
Platform: UNKNOWN
